rezup/__init__.py
rezup/__main__.py
rezup/_actions.py
rezup/_logging.py
rezup/_version.py
rezup/cli.py
rezup/container.py
rezup/exceptions.py
rezup/recipe.py
rezup/rezup.toml
rezup/util.py
rezup/util_env.py
rezup/_vendor/__init__.py
rezup/_vendor/version.py
rezup/_vendor/toml/__init__.py
rezup/_vendor/toml/common.py
rezup/_vendor/toml/decoder.py
rezup/_vendor/toml/encoder.py
rezup/_vendor/toml/ordered.py
rezup/_vendor/toml/tz.py
rezup/launch/README.md
rezup/launch/__init__.py
rezup/launch/shell.py
rezup/launch/up.bat
rezup/launch/up.ps1
rezup_api-2.6.0.dist-info/LICENSE
rezup_api-2.6.0.dist-info/METADATA
rezup_api-2.6.0.dist-info/WHEEL
rezup_api-2.6.0.dist-info/top_level.txt
rezup_api-2.6.0.dist-info/RECORD
