Metadata-Version: 2.1
Name: rezup-api
Version: 2.6.0
Summary: Rez launching environment manager
Home-page: https://github.com/davidlatwe/rezup
Author: davidlatwe
Author-email: davidlatwe@gmail.com
Maintainer: davidlatwe
Maintainer-email: davidlatwe@gmail.com
License: Apache
Project-URL: Source, https://github.com/davidlatwe/rezup
Project-URL: Tracker, https://github.com/davidlatwe/rezup/issues
Keywords: package resolve version build install software management
Platform: any
Classifier: Development Status :: 5 - Production/Stable
Classifier: Intended Audience :: Developers
Classifier: License :: OSI Approved :: Apache Software License
Classifier: Operating System :: MacOS :: MacOS X
Classifier: Operating System :: Microsoft :: Windows
Classifier: Operating System :: POSIX
Classifier: Programming Language :: Python :: 2
Classifier: Programming Language :: Python :: 2.7
Classifier: Programming Language :: Python :: 3
Classifier: Programming Language :: Python :: 3.6
Classifier: Programming Language :: Python :: 3.7
Classifier: Programming Language :: Python :: 3.8
Classifier: Programming Language :: Python :: 3.9
Classifier: Programming Language :: Python :: 3.10
Classifier: Programming Language :: Python :: Implementation :: CPython
Classifier: Topic :: Utilities
Classifier: Topic :: Software Development
Classifier: Topic :: System :: Software Distribution
Requires-Python: !=3.0.*,!=3.1.*,!=3.2.*,!=3.3.*,!=3.4.*,>=2.7
License-File: LICENSE
Requires-Dist: click (>=7.1)
Requires-Dist: distlib (<1,>=0.3.1)
Requires-Dist: colorama
Requires-Dist: virtualenv (<21,>=20.4.4)
Requires-Dist: shellingham (<2,>=1.4.0)
Requires-Dist: python-dotenv (<1,>=0.17)
Requires-Dist: pathlib2 ; python_version < "3.0"
Provides-Extra: docs
Requires-Dist: mkdocs ; extra == 'docs'
Requires-Dist: mkdocs-material ; extra == 'docs'
Requires-Dist: mkdocstrings ; extra == 'docs'
Provides-Extra: tests
Requires-Dist: pytest ; extra == 'tests'
Requires-Dist: mock ; extra == 'tests'
